autoindent.py
autoindent-0.1.2.dist-info/LICENSE
autoindent-0.1.2.dist-info/METADATA
autoindent-0.1.2.dist-info/WHEEL
autoindent-0.1.2.dist-info/top_level.txt
autoindent-0.1.2.dist-info/RECORD
